.bumpversion.cfg
.readthedocs.yaml
CONTRIBUTING.md
LICENSE
MANIFEST.in
Makefile
README.md
pyproject.toml
setup.py
docs/Makefile
docs/conf.py
docs/index.rst
docs/make.bat
docs/pynrm.rst
pynrm/Pedigree.py
pynrm/Simulator.py
pynrm/__init__.py
pynrm/__main__.py
pynrm/nrm.py
pynrm.egg-info/PKG-INFO
pynrm.egg-info/SOURCES.txt
pynrm.egg-info/dependency_links.txt
pynrm.egg-info/requires.txt
pynrm.egg-info/top_level.txt
pynrm/tests/test_nrm.py
pynrm/tests/test_pedigree.py
pynrm/tests/test_simulator.py