Metadata-Version: 2.1
Name: pynrm
Version: 0.1.2
Summary: A python library for animal breeding simulation
Author-email: Kate Jeon <hj2589@columbia.edu>
License:                                  Apache License
Project-URL: repository, https://github.com/katehyerinjeon/pynrm
Classifier: Development Status :: 2 - Pre-Alpha
Classifier: Programming Language :: Python :: Implementation :: CPython
Classifier: Programming Language :: Python :: Implementation :: PyPy
Classifier: Programming Language :: Python :: 3
Classifier: Programming Language :: Python :: 3.7
Classifier: Programming Language :: Python :: 3.8
Classifier: Programming Language :: Python :: 3.9
Classifier: Programming Language :: Python :: 3.10
Classifier: Programming Language :: Python :: 3.11
Requires-Python: >=3.7
Provides-Extra: develop
License-File: LICENSE
